pyumi/__init__.py
pyumi/epw.py
pyumi/geom_ops.py
pyumi/umi_layers.py
pyumi/umi_project.py
pyumi/shoeboxer/__init__.py
pyumi/shoeboxer/hvac_templates.py
pyumi/shoeboxer/shoebox.py
pyumi-0.5.0.dist-info/METADATA
pyumi-0.5.0.dist-info/WHEEL
pyumi-0.5.0.dist-info/top_level.txt
pyumi-0.5.0.dist-info/RECORD
