Metadata-Version: 2.1
Name: pyumi
Version: 0.5.0
Summary: Create and edit umi projects
Home-page: https://github.com/samuelduchesne/pyumi
Author: Samuel Letellier-Duchesne
Author-email: samueld@mit.edu
License: MIT
Platform: UNKNOWN
Classifier: Development Status :: 3 - Alpha
Classifier: Intended Audience :: Science/Research
Classifier: License :: OSI Approved :: MIT License
Classifier: Programming Language :: Python :: 3.7
Classifier: Programming Language :: Python :: 3.8
Classifier: Programming Language :: Python :: 3.9
Requires-Python: >=3.6
Requires-Dist: osmnx (~=1.1.1)
Requires-Dist: tabulate (~=0.8.9)
Requires-Dist: rhino3dm (==7.7.0)
Requires-Dist: chardet (~=4.0.0)
Requires-Dist: archetypal (~=2.2.0)
Provides-Extra: cjio
Requires-Dist: cjio (~=0.6.8) ; extra == 'cjio'
Provides-Extra: dev
Requires-Dist: isort (==5.9.1) ; extra == 'dev'
Requires-Dist: black (==21.6b0) ; extra == 'dev'
Requires-Dist: sphinx (==4.0.2) ; extra == 'dev'
Requires-Dist: pytest (==6.2.4) ; extra == 'dev'
Requires-Dist: pytest-cov (==2.12.1) ; extra == 'dev'
Requires-Dist: pytest-xdist (==2.3.0) ; extra == 'dev'
Requires-Dist: yappi (==1.3.0) ; extra == 'dev'
Requires-Dist: coverage (==5.5) ; extra == 'dev'
